odoo8_addon_base_manifest_extension-8.0.1.0.0-py2.7-nspkg.pth
odoo8_addon_base_manifest_extension-8.0.1.0.0.dist-info/DESCRIPTION.rst
odoo8_addon_base_manifest_extension-8.0.1.0.0.dist-info/METADATA
odoo8_addon_base_manifest_extension-8.0.1.0.0.dist-info/RECORD
odoo8_addon_base_manifest_extension-8.0.1.0.0.dist-info/WHEEL
odoo8_addon_base_manifest_extension-8.0.1.0.0.dist-info/metadata.json
odoo8_addon_base_manifest_extension-8.0.1.0.0.dist-info/namespace_packages.txt
odoo8_addon_base_manifest_extension-8.0.1.0.0.dist-info/top_level.txt
odoo_addons/base_manifest_extension/README.rst
odoo_addons/base_manifest_extension/__init__.py
odoo_addons/base_manifest_extension/__openerp__.py
odoo_addons/base_manifest_extension/hooks.py
odoo_addons/base_manifest_extension/static/description/icon.png
odoo_addons/base_manifest_extension/tests/__init__.py
odoo_addons/base_manifest_extension/tests/test_base_manifest_extension.py
